{"stats":{"minecraft:custom":{"minecraft:mob_kills":12,"minecraft:leave_game":4,"minecraft:time_since_death":140,"minecraft:climb_one_cm":2804,"minecraft:damage_resisted":366,"minecraft:sprint_one_cm":65584,"minecraft:walk_one_cm":118182,"minecraft:drop":29,"minecraft:talked_to_villager":1,"minecraft:play_time":42186,"minecraft:sneak_time":292,"minecraft:deaths":53,"minecraft:jump":699,"minecraft:total_world_time":42186,"minecraft:time_since_rest":175,"minecraft:damage_taken":15492,"minecraft:damage_absorbed":80,"minecraft:damage_dealt":1741,"minecraft:fly_one_cm":182799,"minecraft:player_kills":6,"minecraft:open_chest":7,"minecraft:crouch_one_cm":1045,"minecraft:fall_one_cm":20493,"minecraft:horse_one_cm":28862},"minecraft:killed_by":{"minecraft:ghast":1,"minecraft:player":26,"minecraft:creeper":1,"minecraft:cave_spider":1},"minecraft:mined":{"lucky:lucky_block":61,"minecraft:bamboo_mosaic":1,"minecraft:yellow_wool":1},"minecraft:killed":{"minecraft:pig":2,"minecraft:sheep":6,"minecraft:zombie":2},"minecraft:used":{"minecraft:trader_llama_spawn_egg":1,"minecraft:blue_terracotta":5,"minecraft:tropical_fish":2,"minecraft:iron_sword":7,"minecraft:quartz_stairs":9,"minecraft:wooden_shovel":1,"minecraft:chainmail_chestplate":1,"lucky:lucky_potion":8,"minecraft:cooked_mutton":1,"minecraft:wooden_pickaxe":1,"lucky:lucky_sword":13,"minecraft:creeper_spawn_egg":1,"minecraft:bread":1,"minecraft:iron_pickaxe":26,"minecraft:potion":1,"minecraft:chainmail_boots":1,"minecraft:cooked_porkchop":1},"minecraft:dropped":{"minecraft:stone_hoe":1,"minecraft:daylight_detector":1,"minecraft:oak_pressure_plate":4,"minecraft:crossbow":1,"minecraft:iron_horse_armor":1,"minecraft:saddle":1,"minecraft:oxeye_daisy":15,"minecraft:fermented_spider_eye":6,"minecraft:dandelion":9,"minecraft:pink_tulip":23,"minecraft:stone_axe":2,"minecraft:stone_shovel":1,"minecraft:rotten_flesh":9,"minecraft:azure_bluet":14,"minecraft:poppy":22,"minecraft:allium":15,"minecraft:leather_boots":1,"minecraft:leather_leggings":1,"minecraft:spider_eye":3,"minecraft:painting":4,"minecraft:blue_orchid":7,"minecraft:magma_cream":2},"minecraft:picked_up":{"minecraft:wooden_axe":3,"minecraft:fishing_rod":1,"minecraft:iron_chestplate":3,"minecraft:music_disc_strad":1,"minecraft:wheat":7,"minecraft:allium":26,"minecraft:azure_bluet":24,"minecraft:chainmail_boots":1,"minecraft:nether_wart":3,"minecraft:iron_trapdoor":2,"minecraft:anvil":3,"minecraft:prismarine_shard":19,"minecraft:leather_leggings":1,"minecraft:rabbit_stew":1,"minecraft:yellow_wool":2,"minecraft:redstone_lamp":4,"minecraft:diamond_sword":2,"minecraft:wooden_pickaxe":4,"minecraft:pink_wool":1,"minecraft:cooked_rabbit":1,"minecraft:potion":2,"minecraft:enchanted_book":26,"minecraft:diamond_horse_armor":1,"minecraft:stray_spawn_egg":1,"minecraft:heavy_weighted_pressure_plate":1,"minecraft:oak_trapdoor":2,"minecraft:string":3,"lucky:lucky_potion":69,"minecraft:cooked_salmon":1,"minecraft:wooden_sword":3,"minecraft:iron_leggings":2,"minecraft:sticky_piston":4,"minecraft:vex_spawn_egg":1,"minecraft:pufferfish":13,"minecraft:magenta_wool":1,"minecraft:blue_orchid":20,"minecraft:diamond_leggings":1,"minecraft:gold_nugget":7,"minecraft:comparator":2,"lucky:lucky_sword":6,"minecraft:bucket":3,"minecraft:light_weighted_pressure_plate":1,"minecraft:redstone_torch":8,"minecraft:ender_eye":9,"minecraft:enchanted_golden_apple":1,"minecraft:wooden_shovel":2,"minecraft:poppy":38,"minecraft:iron_pickaxe":1,"minecraft:light_gray_wool":1,"minecraft:quartz_stairs":25,"minecraft:piston":4,"minecraft:iron_boots":1,"minecraft:blue_wool":2,"minecraft:stick":5,"minecraft:jukebox":1,"minecraft:oak_door":1,"minecraft:bowl":1,"minecraft:note_block":1,"minecraft:porkchop":5,"minecraft:stone_button":2,"minecraft:cookie":33,"minecraft:carrot":9,"minecraft:redstone":46,"minecraft:green_terracotta":19,"minecraft:drowned_spawn_egg":1,"minecraft:prismarine_crystals":28,"minecraft:iron_horse_armor":3,"minecraft:rabbit_foot":2,"minecraft:stone_pressure_plate":2,"minecraft:tnt":14,"minecraft:stone_sword":3,"minecraft:arrow":19,"minecraft:stone_shovel":3,"minecraft:rotten_flesh":12,"minecraft:diamond_chestplate":1,"minecraft:tropical_fish":6,"minecraft:pink_tulip":48,"minecraft:saddle":12,"minecraft:glistering_melon_slice":6,"minecraft:blaze_rod":3,"minecraft:obsidian":27,"minecraft:mutton":17,"minecraft:white_wool":1,"minecraft:blaze_powder":3,"minecraft:oxeye_daisy":38,"minecraft:leather_chestplate":2,"minecraft:magma_cream":4,"minecraft:cooked_beef":2,"minecraft:repeater":8,"minecraft:golden_carrot":3,"minecraft:iron_door":1,"minecraft:tripwire_hook":2,"minecraft:water_bucket":1,"minecraft:salmon":7,"minecraft:brown_wool":1,"minecraft:end_portal_frame":1,"minecraft:potato":59,"minecraft:tadpole_spawn_egg":1,"minecraft:mushroom_stew":1,"minecraft:chainmail_chestplate":1,"minecraft:wooden_hoe":4,"lucky:lucky_bow":5,"minecraft:cooked_mutton":9,"minecraft:leather_boots":1,"minecraft:bone":1,"minecraft:apple":2,"minecraft:bow":1,"minecraft:creeper_spawn_egg":1,"minecraft:oak_fence_gate":1,"minecraft:stone_pickaxe":3,"minecraft:rabbit":1,"minecraft:prismarine":32,"minecraft:iron_sword":2,"minecraft:stone_hoe":3,"minecraft:ghast_tear":2,"minecraft:milk_bucket":2,"minecraft:black_terracotta":4,"minecraft:cooked_porkchop":4,"minecraft:strider_spawn_egg":1,"minecraft:daylight_detector":2,"minecraft:dropper":20,"minecraft:dandelion":32,"minecraft:oak_pressure_plate":4,"minecraft:poisonous_potato":17,"minecraft:lava_bucket":1,"minecraft:melon":2,"minecraft:fermented_spider_eye":15,"minecraft:sea_lantern":12,"minecraft:spider_eye":11,"minecraft:orange_wool":1,"minecraft:diamond_shovel":1,"minecraft:dispenser":2,"minecraft:blue_terracotta":5,"minecraft:sugar":26,"minecraft:black_concrete":9,"minecraft:trader_llama_spawn_egg":1,"minecraft:diamond":5,"minecraft:stone_axe":4,"minecraft:lever":2,"minecraft:iron_helmet":3,"minecraft:crossbow":3,"minecraft:diamond_axe":1,"minecraft:painting":4,"minecraft:golden_apple":3,"minecraft:golden_horse_armor":3,"minecraft:bread":2,"minecraft:oak_button":2,"minecraft:baked_potato":33,"minecraft:diamond_pickaxe":2,"minecraft:hopper":4,"minecraft:nether_star":1,"minecraft:ender_pearl":11}},"DataVersion":3465}